ChatGPTHandler.py
ChatGPTOps-0.0.1.dist-info/METADATA
ChatGPTOps-0.0.1.dist-info/WHEEL
ChatGPTOps-0.0.1.dist-info/top_level.txt
ChatGPTOps-0.0.1.dist-info/RECORD
