Metadata-Version: 2.1
Name: ChatGPTOps
Version: 0.0.1
Summary: Ask chatGPT llm to investigate your unhandled exceptions & file github issues with proposed fixes without filing duplicate issues
Home-page: https://github.com/karmacomputing/chatgptops
Author: Chris Simpson
Author-email: oss@karmacomputing.co.uk
License: UNKNOWN
Platform: UNKNOWN
Classifier: License :: OSI Approved :: GNU General Public License v3 (GPLv3)
Requires-Python: >=3.9
Requires-Dist: openai
Requires-Dist: unhandled-exception-logger
